dls_bluesky_core/__init__.py
dls_bluesky_core/__main__.py
dls_bluesky_core/_version.py
dls_bluesky_core/core/__init__.py
dls_bluesky_core/core/coordination.py
dls_bluesky_core/core/maths.py
dls_bluesky_core/core/scanspecs.py
dls_bluesky_core/core/types.py
dls_bluesky_core/plans/__init__.py
dls_bluesky_core/plans/scanspec.py
dls_bluesky_core/plans/wrapped.py
dls_bluesky_core/stubs/__init__.py
dls_bluesky_core/stubs/wrapped.py
dls_bluesky_core-0.0.4.dist-info/LICENSE
dls_bluesky_core-0.0.4.dist-info/METADATA
dls_bluesky_core-0.0.4.dist-info/WHEEL
dls_bluesky_core-0.0.4.dist-info/entry_points.txt
dls_bluesky_core-0.0.4.dist-info/top_level.txt
dls_bluesky_core-0.0.4.dist-info/RECORD
